{
  "members": [
    {
      "id": "3",
      "password": "3333",
      "name": "이영희",
      "phone": "010-3456-7890",
      "birth": "2000-12-31"
    },
    {
      "id": "4",
      "password": "4444",
      "name": "박민수",
      "phone": "010-4567-8901",
      "birth": "1998-07-20"
    },
    {
      "id": "c840",
      "name": "박윤영",
      "phone": "010-7274-7454",
      "birth": "2001-05-14"
    },
    {
      "id": "df01",
      "name": "홍길동",
      "phone": "010-1234-1234",
      "birth": "2025-12-11"
    },
    {
      "id": "fc37",
      "name": "김윤영",
      "phone": "010-1111-1111",
      "birth": "2025-12-10"
    },
    {
      "id": "8bb3",
      "name": "김윤영",
      "phone": "010-1234-1234",
      "birth": "2001-12-01"
    },
    {
      "id": "4440",
      "name": "집언제가냐",
      "phone": "010-1232-1234",
      "birth": "2025-12-11"
    }
  ],
  "products": [
    {
      "id": 1,
      "name": "베이직 반팔 티셔츠",
      "company": "YUN FASHION",
      "category": "FASHION",
      "price": 19900,
      "thumbnailUrl": "/images/fashion_1.jpg",
      "isSoldOut": false,
      "isNew": true,
      "reviewCount": 124,
      "rating": 4.5,
      "descriptionImages": ["/images/fashion_1_1.jpg"],
      "content": "<p>데일리로 입기 좋은 베이직 반팔 티셔츠</p>",
      "stock": 52
    },
    {
      "id": 2,
      "name": "슬림 데님 팬츠",
      "company": "YUN FASHION",
      "category": "FASHION",
      "price": 49900,
      "thumbnailUrl": "/images/fashion_2.jpg",
      "isSoldOut": false,
      "isNew": false,
      "reviewCount": 87,
      "rating": 4.3,
      "descriptionImages": ["/images/fashion_2_1.jpg"],
      "content": "<p>슬림핏 데님 팬츠</p>",
      "stock": 31
    },
    {
      "id": 3,
      "name": "오버핏 후드",
      "company": "STREET LAB",
      "category": "FASHION",
      "price": 59000,
      "thumbnailUrl": "/images/fashion_3.jpg",
      "isSoldOut": false,
      "isNew": true,
      "reviewCount": 210,
      "rating": 4.6,
      "descriptionImages": ["/images/fashion_3_1.jpg"],
      "content": "<p>트렌디한 오버핏 후드</p>",
      "stock": 40
    },
    {
      "id": 4,
      "name": "울 니트",
      "company": "MODERN WEAR",
      "category": "FASHION",
      "price": 69000,
      "thumbnailUrl": "/images/fashion_4.jpg",
      "isSoldOut": false,
      "isNew": false,
      "reviewCount": 55,
      "rating": 4.2,
      "descriptionImages": ["/images/fashion_4_1.jpg"],
      "content": "<p>보온성 좋은 울 니트</p>",
      "stock": 20
    },
    {
      "id": 5,
      "name": "트렌치 코트",
      "company": "MODERN WEAR",
      "category": "FASHION",
      "price": 159000,
      "thumbnailUrl": "/images/fashion_5.jpg",
      "isSoldOut": false,
      "isNew": true,
      "reviewCount": 98,
      "rating": 4.7,
      "descriptionImages": ["/images/fashion_5_1.jpg"],
      "content": "<p>클래식 트렌치 코트</p>",
      "stock": 15
    },
    {
      "id": 6,
      "name": "슬랙스 팬츠",
      "company": "OFFICE LOOK",
      "category": "FASHION",
      "price": 62000,
      "thumbnailUrl": "/images/fashion_6.jpg",
      "isSoldOut": false,
      "isNew": false,
      "reviewCount": 76,
      "rating": 4.1,
      "descriptionImages": ["/images/fashion_6_1.jpg"],
      "content": "<p>출근룩 슬랙스</p>",
      "stock": 28
    },
    {
      "id": 7,
      "name": "린넨 셔츠",
      "company": "SUMMER FIT",
      "category": "FASHION",
      "price": 45000,
      "thumbnailUrl": "/images/fashion_7.jpg",
      "isSoldOut": false,
      "isNew": true,
      "reviewCount": 61,
      "rating": 4.4,
      "descriptionImages": ["/images/fashion_7_1.jpg"],
      "content": "<p>통기성 좋은 린넨 셔츠</p>",
      "stock": 33
    },
    {
      "id": 8,
      "name": "볼캡 모자",
      "company": "STREET LAB",
      "category": "FASHION",
      "price": 29000,
      "thumbnailUrl": "/images/fashion_8.jpg",
      "isSoldOut": false,
      "isNew": false,
      "reviewCount": 142,
      "rating": 4.8,
      "descriptionImages": ["/images/fashion_8_1.jpg"],
      "content": "<p>데일리 볼캡</p>",
      "stock": 120
    },
    {
      "id": 9,
      "name": "패딩 점퍼",
      "company": "WINTER GEAR",
      "category": "FASHION",
      "price": 189000,
      "thumbnailUrl": "/images/fashion_9.jpg",
      "isSoldOut": true,
      "isNew": false,
      "reviewCount": 310,
      "rating": 4.9,
      "descriptionImages": ["/images/fashion_9_1.jpg"],
      "content": "<p>방한용 패딩</p>",
      "stock": 0
    },
    {
      "id": 10,
      "name": "니트 가디건",
      "company": "MODERN WEAR",
      "category": "FASHION",
      "price": 72000,
      "thumbnailUrl": "/images/fashion_10.jpg",
      "isSoldOut": false,
      "isNew": false,
      "reviewCount": 44,
      "rating": 4.0,
      "descriptionImages": ["/images/fashion_10_1.jpg"],
      "content": "<p>베이직 가디건</p>",
      "stock": 19
    },
    {
      "id": 11,
      "name": "비타민C 세럼",
      "company": "PURE BEAUTY",
      "category": "BEAUTY",
      "price": 28900,
      "thumbnailUrl": "/images/beauty_1.jpg",
      "isSoldOut": false,
      "isNew": true,
      "reviewCount": 412,
      "rating": 4.7,
      "descriptionImages": ["/images/beauty_1_1.jpg"],
      "content": "<p>미백 세럼</p>",
      "stock": 120
    },
    {
      "id": 12,
      "name": "수분 크림",
      "company": "PURE BEAUTY",
      "category": "BEAUTY",
      "price": 32000,
      "thumbnailUrl": "/images/beauty_2.jpg",
      "isSoldOut": false,
      "isNew": false,
      "reviewCount": 233,
      "rating": 4.5,
      "descriptionImages": ["/images/beauty_2_1.jpg"],
      "content": "<p>고보습 크림</p>",
      "stock": 90
    },
    {
      "id": 13,
      "name": "선크림 SPF50+",
      "company": "SKIN SAFE",
      "category": "BEAUTY",
      "price": 21000,
      "thumbnailUrl": "/images/beauty_3.jpg",
      "isSoldOut": false,
      "isNew": true,
      "reviewCount": 521,
      "rating": 4.8,
      "descriptionImages": ["/images/beauty_3_1.jpg"],
      "content": "<p>자외선 차단</p>",
      "stock": 150
    },
    {
      "id": 14,
      "name": "클렌징 폼",
      "company": "SKIN SAFE",
      "category": "BEAUTY",
      "price": 15000,
      "thumbnailUrl": "/images/beauty_4.jpg",
      "isSoldOut": false,
      "isNew": false,
      "reviewCount": 180,
      "rating": 4.2,
      "descriptionImages": ["/images/beauty_4_1.jpg"],
      "content": "<p>저자극 클렌징</p>",
      "stock": 110
    },
    {
      "id": 15,
      "name": "토너",
      "company": "PURE BEAUTY",
      "category": "BEAUTY",
      "price": 18000,
      "thumbnailUrl": "/images/beauty_5.jpg",
      "isSoldOut": false,
      "isNew": false,
      "reviewCount": 99,
      "rating": 4.1,
      "descriptionImages": ["/images/beauty_5_1.jpg"],
      "content": "<p>피부 결 정돈</p>",
      "stock": 70
    },
    {
      "id": 16,
      "name": "아이크림",
      "company": "AGE CARE",
      "category": "BEAUTY",
      "price": 39000,
      "thumbnailUrl": "/images/beauty_6.jpg",
      "isSoldOut": false,
      "isNew": true,
      "reviewCount": 65,
      "rating": 4.4,
      "descriptionImages": ["/images/beauty_6_1.jpg"],
      "content": "<p>주름 케어</p>",
      "stock": 42
    },
    {
      "id": 17,
      "name": "마스크팩 10매",
      "company": "SKIN SAFE",
      "category": "BEAUTY",
      "price": 12000,
      "thumbnailUrl": "/images/beauty_7.jpg",
      "isSoldOut": false,
      "isNew": false,
      "reviewCount": 640,
      "rating": 4.9,
      "descriptionImages": ["/images/beauty_7_1.jpg"],
      "content": "<p>집중 보습</p>",
      "stock": 300
    },
    {
      "id": 18,
      "name": "에센스",
      "company": "PURE BEAUTY",
      "category": "BEAUTY",
      "price": 35000,
      "thumbnailUrl": "/images/beauty_8.jpg",
      "isSoldOut": false,
      "isNew": false,
      "reviewCount": 87,
      "rating": 4.0,
      "descriptionImages": ["/images/beauty_8_1.jpg"],
      "content": "<p>영양 공급</p>",
      "stock": 55
    },
    {
      "id": 19,
      "name": "립밤",
      "company": "LIP CARE",
      "category": "BEAUTY",
      "price": 8000,
      "thumbnailUrl": "/images/beauty_9.jpg",
      "isSoldOut": false,
      "isNew": true,
      "reviewCount": 430,
      "rating": 4.6,
      "descriptionImages": ["/images/beauty_9_1.jpg"],
      "content": "<p>보습 립밤</p>",
      "stock": 500
    },
    {
      "id": 20,
      "name": "미스트",
      "company": "PURE BEAUTY",
      "category": "BEAUTY",
      "price": 17000,
      "thumbnailUrl": "/images/beauty_10.jpg",
      "isSoldOut": false,
      "isNew": false,
      "reviewCount": 73,
      "rating": 4.1,
      "descriptionImages": ["/images/beauty_10_1.jpg"],
      "content": "<p>수분 미스트</p>",
      "stock": 88
    },
    {
      "id": 21,
      "name": "유기농 그래놀라",
      "company": "GOOD FOOD",
      "category": "FOOD",
      "price": 15900,
      "thumbnailUrl": "/images/food_1.jpg",
      "isSoldOut": false,
      "isNew": false,
      "reviewCount": 210,
      "rating": 4.6,
      "descriptionImages": ["/images/food_1_1.jpg"],
      "content": "<p>아침 식사용 유기농 그래놀라</p>",
      "stock": 200
    },
    {
      "id": 22,
      "name": "단백질 쉐이크",
      "company": "PRO NUTRITION",
      "category": "FOOD",
      "price": 34900,
      "thumbnailUrl": "/images/food_2.jpg",
      "isSoldOut": false,
      "isNew": true,
      "reviewCount": 532,
      "rating": 4.8,
      "descriptionImages": ["/images/food_2_1.jpg"],
      "content": "<p>운동 후 섭취용 단백질 쉐이크</p>",
      "stock": 120
    },
    {
      "id": 23,
      "name": "콜드브루 원액",
      "company": "COFFEE LAB",
      "category": "FOOD",
      "price": 18900,
      "thumbnailUrl": "/images/food_3.jpg",
      "isSoldOut": false,
      "isNew": false,
      "reviewCount": 98,
      "rating": 4.3,
      "descriptionImages": ["/images/food_3_1.jpg"],
      "content": "<p>깊은 풍미의 콜드브루 커피</p>",
      "stock": 65
    },
    {
      "id": 24,
      "name": "저당 초콜릿",
      "company": "HEALTHY BITE",
      "category": "FOOD",
      "price": 12900,
      "thumbnailUrl": "/images/food_4.jpg",
      "isSoldOut": false,
      "isNew": true,
      "reviewCount": 310,
      "rating": 4.5,
      "descriptionImages": ["/images/food_4_1.jpg"],
      "content": "<p>당류를 낮춘 다크 초콜릿</p>",
      "stock": 180
    },
    {
      "id": 25,
      "name": "견과류 믹스",
      "company": "NUT FARM",
      "category": "FOOD",
      "price": 22900,
      "thumbnailUrl": "/images/food_5.jpg",
      "isSoldOut": false,
      "isNew": false,
      "reviewCount": 144,
      "rating": 4.4,
      "descriptionImages": ["/images/food_5_1.jpg"],
      "content": "<p>하루 한 봉 견과류 믹스</p>",
      "stock": 250
    },
    {
      "id": 26,
      "name": "그릭 요거트",
      "company": "DAIRY FRESH",
      "category": "FOOD",
      "price": 9900,
      "thumbnailUrl": "/images/food_6.jpg",
      "isSoldOut": false,
      "isNew": false,
      "reviewCount": 420,
      "rating": 4.7,
      "descriptionImages": ["/images/food_6_1.jpg"],
      "content": "<p>고단백 그릭 요거트</p>",
      "stock": 90
    },
    {
      "id": 27,
      "name": "프로틴 바",
      "company": "PRO NUTRITION",
      "category": "FOOD",
      "price": 2500,
      "thumbnailUrl": "/images/food_7.jpg",
      "isSoldOut": false,
      "isNew": true,
      "reviewCount": 610,
      "rating": 4.6,
      "descriptionImages": ["/images/food_7_1.jpg"],
      "content": "<p>간편하게 먹는 단백질 바</p>",
      "stock": 1000
    },
    {
      "id": 28,
      "name": "유기농 꿀",
      "company": "NATURE FARM",
      "category": "FOOD",
      "price": 27900,
      "thumbnailUrl": "/images/food_8.jpg",
      "isSoldOut": false,
      "isNew": false,
      "reviewCount": 76,
      "rating": 4.2,
      "descriptionImages": ["/images/food_8_1.jpg"],
      "content": "<p>100% 유기농 천연 꿀</p>",
      "stock": 45
    },
    {
      "id": 29,
      "name": "즉석 닭가슴살",
      "company": "FIT FOOD",
      "category": "FOOD",
      "price": 3200,
      "thumbnailUrl": "/images/food_9.jpg",
      "isSoldOut": false,
      "isNew": true,
      "reviewCount": 890,
      "rating": 4.8,
      "descriptionImages": ["/images/food_9_1.jpg"],
      "content": "<p>전자레인지 조리 가능</p>",
      "stock": 500
    },
    {
      "id": 30,
      "name": "현미밥",
      "company": "GOOD FOOD",
      "category": "FOOD",
      "price": 1500,
      "thumbnailUrl": "/images/food_10.jpg",
      "isSoldOut": false,
      "isNew": false,
      "reviewCount": 260,
      "rating": 4.1,
      "descriptionImages": ["/images/food_10_1.jpg"],
      "content": "<p>간편한 즉석 현미밥</p>",
      "stock": 700
    },
    {
      "id": 31,
      "name": "무선 블루투스 이어폰",
      "company": "TECH ONE",
      "category": "ELECTRONICS",
      "price": 129000,
      "thumbnailUrl": "/images/electronics_1.jpg",
      "isSoldOut": false,
      "isNew": true,
      "reviewCount": 982,
      "rating": 4.8,
      "descriptionImages": ["/images/electronics_1_1.jpg"],
      "content": "<p>노이즈 캔슬링 지원</p>",
      "stock": 45
    },
    {
      "id": 32,
      "name": "기계식 키보드",
      "company": "KEY LAB",
      "category": "ELECTRONICS",
      "price": 159000,
      "thumbnailUrl": "/images/electronics_2.jpg",
      "isSoldOut": false,
      "isNew": false,
      "reviewCount": 340,
      "rating": 4.6,
      "descriptionImages": ["/images/electronics_2_1.jpg"],
      "content": "<p>청축 기계식 키보드</p>",
      "stock": 60
    },
    {
      "id": 33,
      "name": "27인치 모니터",
      "company": "VISION TECH",
      "category": "ELECTRONICS",
      "price": 289000,
      "thumbnailUrl": "/images/electronics_3.jpg",
      "isSoldOut": false,
      "isNew": true,
      "reviewCount": 190,
      "rating": 4.5,
      "descriptionImages": ["/images/electronics_3_1.jpg"],
      "content": "<p>QHD 해상도 모니터</p>",
      "stock": 22
    },
    {
      "id": 34,
      "name": "무선 마우스",
      "company": "KEY LAB",
      "category": "ELECTRONICS",
      "price": 59000,
      "thumbnailUrl": "/images/electronics_4.jpg",
      "isSoldOut": false,
      "isNew": false,
      "reviewCount": 780,
      "rating": 4.7,
      "descriptionImages": ["/images/electronics_4_1.jpg"],
      "content": "<p>저소음 무선 마우스</p>",
      "stock": 130
    },
    {
      "id": 35,
      "name": "스마트 워치",
      "company": "TECH ONE",
      "category": "ELECTRONICS",
      "price": 249000,
      "thumbnailUrl": "/images/electronics_5.jpg",
      "isSoldOut": false,
      "isNew": true,
      "reviewCount": 410,
      "rating": 4.4,
      "descriptionImages": ["/images/electronics_5_1.jpg"],
      "content": "<p>운동 기록 지원</p>",
      "stock": 38
    },
    {
      "id": 36,
      "name": "태블릿 거치대",
      "company": "DESK LAB",
      "category": "ELECTRONICS",
      "price": 29000,
      "thumbnailUrl": "/images/electronics_6.jpg",
      "isSoldOut": false,
      "isNew": false,
      "reviewCount": 96,
      "rating": 4.2,
      "descriptionImages": ["/images/electronics_6_1.jpg"],
      "content": "<p>알루미늄 거치대</p>",
      "stock": 85
    },
    {
      "id": 37,
      "name": "USB-C 허브",
      "company": "DESK LAB",
      "category": "ELECTRONICS",
      "price": 69000,
      "thumbnailUrl": "/images/electronics_7.jpg",
      "isSoldOut": false,
      "isNew": true,
      "reviewCount": 510,
      "rating": 4.8,
      "descriptionImages": ["/images/electronics_7_1.jpg"],
      "content": "<p>멀티포트 허브</p>",
      "stock": 95
    },
    {
      "id": 38,
      "name": "외장 SSD 1TB",
      "company": "STORAGE PRO",
      "category": "ELECTRONICS",
      "price": 179000,
      "thumbnailUrl": "/images/electronics_8.jpg",
      "isSoldOut": false,
      "isNew": false,
      "reviewCount": 260,
      "rating": 4.6,
      "descriptionImages": ["/images/electronics_8_1.jpg"],
      "content": "<p>고속 외장 SSD</p>",
      "stock": 40
    },
    {
      "id": 39,
      "name": "웹캠",
      "company": "VISION TECH",
      "category": "ELECTRONICS",
      "price": 89000,
      "thumbnailUrl": "/images/electronics_9.jpg",
      "isSoldOut": false,
      "isNew": false,
      "reviewCount": 170,
      "rating": 4.1,
      "descriptionImages": ["/images/electronics_9_1.jpg"],
      "content": "<p>FHD 화상 회의용</p>",
      "stock": 58
    },
    {
      "id": 40,
      "name": "노이즈 캔슬링 헤드폰",
      "company": "SOUND MAX",
      "category": "ELECTRONICS",
      "price": 329000,
      "thumbnailUrl": "/images/electronics_10.jpg",
      "isSoldOut": true,
      "isNew": false,
      "reviewCount": 920,
      "rating": 4.9,
      "descriptionImages": ["/images/electronics_10_1.jpg"],
      "content": "<p>프리미엄 헤드폰</p>",
      "stock": 0
    },
    {
      "id": 41,
      "name": "아로마 디퓨저",
      "company": "HOME PLUS",
      "category": "HOME_LIVING",
      "price": 39900,
      "thumbnailUrl": "/images/home_1.jpg",
      "isSoldOut": false,
      "isNew": false,
      "reviewCount": 67,
      "rating": 4.2,
      "descriptionImages": ["/images/home_1_1.jpg"],
      "content": "<p>은은한 향으로 공간을 채워주는 디퓨저</p>",
      "stock": 80
    },
    {
      "id": 42,
      "name": "극세사 타월 세트",
      "company": "DAILY HOME",
      "category": "HOME_LIVING",
      "price": 25900,
      "thumbnailUrl": "/images/home_2.jpg",
      "isSoldOut": false,
      "isNew": true,
      "reviewCount": 210,
      "rating": 4.6,
      "descriptionImages": ["/images/home_2_1.jpg"],
      "content": "<p>흡수력 좋은 극세사 타월</p>",
      "stock": 150
    },
    {
      "id": 43,
      "name": "침구 이불 세트",
      "company": "SLEEP WELL",
      "category": "HOME_LIVING",
      "price": 89000,
      "thumbnailUrl": "/images/home_3.jpg",
      "isSoldOut": false,
      "isNew": false,
      "reviewCount": 134,
      "rating": 4.4,
      "descriptionImages": ["/images/home_3_1.jpg"],
      "content": "<p>사계절용 침구 세트</p>",
      "stock": 42
    },
    {
      "id": 44,
      "name": "무드 조명 스탠드",
      "company": "LIGHT LAB",
      "category": "HOME_LIVING",
      "price": 54900,
      "thumbnailUrl": "/images/home_4.jpg",
      "isSoldOut": false,
      "isNew": true,
      "reviewCount": 98,
      "rating": 4.5,
      "descriptionImages": ["/images/home_4_1.jpg"],
      "content": "<p>분위기 연출용 무드 조명</p>",
      "stock": 65
    },
    {
      "id": 45,
      "name": "전기 주전자",
      "company": "KITCHEN PRO",
      "category": "HOME_LIVING",
      "price": 49000,
      "thumbnailUrl": "/images/home_5.jpg",
      "isSoldOut": false,
      "isNew": false,
      "reviewCount": 320,
      "rating": 4.7,
      "descriptionImages": ["/images/home_5_1.jpg"],
      "content": "<p>스테인리스 전기 주전자</p>",
      "stock": 110
    },
    {
      "id": 46,
      "name": "세탁 바구니",
      "company": "DAILY HOME",
      "category": "HOME_LIVING",
      "price": 19900,
      "thumbnailUrl": "/images/home_6.jpg",
      "isSoldOut": false,
      "isNew": false,
      "reviewCount": 76,
      "rating": 4.1,
      "descriptionImages": ["/images/home_6_1.jpg"],
      "content": "<p>접이식 세탁 바구니</p>",
      "stock": 95
    },
    {
      "id": 47,
      "name": "주방 수납 정리함",
      "company": "KITCHEN PRO",
      "category": "HOME_LIVING",
      "price": 32900,
      "thumbnailUrl": "/images/home_7.jpg",
      "isSoldOut": false,
      "isNew": true,
      "reviewCount": 145,
      "rating": 4.3,
      "descriptionImages": ["/images/home_7_1.jpg"],
      "content": "<p>주방 공간 활용 수납함</p>",
      "stock": 130
    },
    {
      "id": 48,
      "name": "욕실 슬리퍼",
      "company": "DAILY HOME",
      "category": "HOME_LIVING",
      "price": 12900,
      "thumbnailUrl": "/images/home_8.jpg",
      "isSoldOut": false,
      "isNew": false,
      "reviewCount": 260,
      "rating": 4.0,
      "descriptionImages": ["/images/home_8_1.jpg"],
      "content": "<p>미끄럼 방지 욕실 슬리퍼</p>",
      "stock": 300
    },
    {
      "id": 49,
      "name": "공기청정 식물",
      "company": "GREEN LIFE",
      "category": "HOME_LIVING",
      "price": 35900,
      "thumbnailUrl": "/images/home_9.jpg",
      "isSoldOut": false,
      "isNew": true,
      "reviewCount": 54,
      "rating": 4.5,
      "descriptionImages": ["/images/home_9_1.jpg"],
      "content": "<p>실내 공기 정화 식물</p>",
      "stock": 28
    },
    {
      "id": 50,
      "name": "패브릭 소파 커버",
      "company": "SLEEP WELL",
      "category": "HOME_LIVING",
      "price": 45900,
      "thumbnailUrl": "/images/home_10.jpg",
      "isSoldOut": false,
      "isNew": false,
      "reviewCount": 88,
      "rating": 4.2,
      "descriptionImages": ["/images/home_10_1.jpg"],
      "content": "<p>교체형 패브릭 소파 커버</p>",
      "stock": 70
    },
    {
      "id": 51,
      "name": "원목 식탁",
      "company": "INTERIOR LAB",
      "category": "FURNITURE_INTERIOR",
      "price": 399000,
      "thumbnailUrl": "/images/furniture_1.jpg",
      "isSoldOut": false,
      "isNew": true,
      "reviewCount": 34,
      "rating": 4.4,
      "descriptionImages": ["/images/furniture_1_1.jpg"],
      "content": "<p>내추럴 디자인 원목 식탁</p>",
      "stock": 12
    },
    {
      "id": 52,
      "name": "패브릭 2인 소파",
      "company": "INTERIOR LAB",
      "category": "FURNITURE_INTERIOR",
      "price": 589000,
      "thumbnailUrl": "/images/furniture_2.jpg",
      "isSoldOut": false,
      "isNew": false,
      "reviewCount": 78,
      "rating": 4.6,
      "descriptionImages": ["/images/furniture_2_1.jpg"],
      "content": "<p>편안한 착석감의 2인 소파</p>",
      "stock": 9
    },
    {
      "id": 53,
      "name": "책장 수납장",
      "company": "WOOD LINE",
      "category": "FURNITURE_INTERIOR",
      "price": 219000,
      "thumbnailUrl": "/images/furniture_3.jpg",
      "isSoldOut": false,
      "isNew": false,
      "reviewCount": 56,
      "rating": 4.3,
      "descriptionImages": ["/images/furniture_3_1.jpg"],
      "content": "<p>다용도 수납 책장</p>",
      "stock": 20
    },
    {
      "id": 54,
      "name": "컴퓨터 책상",
      "company": "DESK LAB",
      "category": "FURNITURE_INTERIOR",
      "price": 179000,
      "thumbnailUrl": "/images/furniture_4.jpg",
      "isSoldOut": false,
      "isNew": true,
      "reviewCount": 140,
      "rating": 4.5,
      "descriptionImages": ["/images/furniture_4_1.jpg"],
      "content": "<p>미니멀 디자인 책상</p>",
      "stock": 33
    },
    {
      "id": 55,
      "name": "의자 세트",
      "company": "DESK LAB",
      "category": "FURNITURE_INTERIOR",
      "price": 129000,
      "thumbnailUrl": "/images/furniture_5.jpg",
      "isSoldOut": false,
      "isNew": false,
      "reviewCount": 190,
      "rating": 4.4,
      "descriptionImages": ["/images/furniture_5_1.jpg"],
      "content": "<p>인체공학 디자인 의자</p>",
      "stock": 45
    },
    {
      "id": 56,
      "name": "협탁",
      "company": "WOOD LINE",
      "category": "FURNITURE_INTERIOR",
      "price": 99000,
      "thumbnailUrl": "/images/furniture_6.jpg",
      "isSoldOut": false,
      "isNew": false,
      "reviewCount": 42,
      "rating": 4.1,
      "descriptionImages": ["/images/furniture_6_1.jpg"],
      "content": "<p>침실용 원목 협탁</p>",
      "stock": 25
    },
    {
      "id": 57,
      "name": "거실 테이블",
      "company": "INTERIOR LAB",
      "category": "FURNITURE_INTERIOR",
      "price": 249000,
      "thumbnailUrl": "/images/furniture_7.jpg",
      "isSoldOut": false,
      "isNew": true,
      "reviewCount": 61,
      "rating": 4.5,
      "descriptionImages": ["/images/furniture_7_1.jpg"],
      "content": "<p>모던 스타일 거실 테이블</p>",
      "stock": 18
    },
    {
      "id": 58,
      "name": "드레스룸 행거",
      "company": "SPACE PLUS",
      "category": "FURNITURE_INTERIOR",
      "price": 139000,
      "thumbnailUrl": "/images/furniture_8.jpg",
      "isSoldOut": false,
      "isNew": false,
      "reviewCount": 83,
      "rating": 4.2,
      "descriptionImages": ["/images/furniture_8_1.jpg"],
      "content": "<p>이동식 드레스룸 행거</p>",
      "stock": 50
    },
    {
      "id": 59,
      "name": "수납 벤치",
      "company": "SPACE PLUS",
      "category": "FURNITURE_INTERIOR",
      "price": 159000,
      "thumbnailUrl": "/images/furniture_9.jpg",
      "isSoldOut": false,
      "isNew": true,
      "reviewCount": 29,
      "rating": 4.3,
      "descriptionImages": ["/images/furniture_9_1.jpg"],
      "content": "<p>수납 가능한 벤치형 가구</p>",
      "stock": 14
    },
    {
      "id": 60,
      "name": "침대 프레임",
      "company": "SLEEP WELL",
      "category": "FURNITURE_INTERIOR",
      "price": 459000,
      "thumbnailUrl": "/images/furniture_10.jpg",
      "isSoldOut": false,
      "isNew": false,
      "reviewCount": 101,
      "rating": 4.6,
      "descriptionImages": ["/images/furniture_10_1.jpg"],
      "content": "<p>퀸 사이즈 침대 프레임</p>",
      "stock": 8
    },
    {
      "id": 61,
      "name": "프리미엄 요가 매트",
      "company": "ZenMove",
      "category": "SPORTS_LEISURE",
      "price": 39000,
      "thumbnailUrl": "/images/sports/yoga_mat_1.jpg",
      "isSoldOut": false,
      "isNew": true,
      "reviewCount": 88,
      "rating": 4.7,
      "descriptionImages": ["/images/sports/yoga_mat_1_1.jpg"],
      "content": "<p>미끄럼 방지 기능이 뛰어난 요가 매트입니다.</p>",
      "stock": 42
    },
    {
      "id": 62,
      "name": "조절형 덤벨 세트",
      "company": "PowerFlex",
      "category": "SPORTS_LEISURE",
      "price": 129000,
      "thumbnailUrl": "/images/sports/dumbbell_1.jpg",
      "isSoldOut": false,
      "isNew": false,
      "reviewCount": 156,
      "rating": 4.6,
      "descriptionImages": ["/images/sports/dumbbell_1_1.jpg"],
      "content": "<p>홈트레이닝에 최적화된 덤벨 세트.</p>",
      "stock": 18
    },
    {
      "id": 63,
      "name": "러닝화 에어핏",
      "company": "RunLab",
      "category": "SPORTS_LEISURE",
      "price": 99000,
      "thumbnailUrl": "/images/sports/running_shoes_1.jpg",
      "isSoldOut": false,
      "isNew": true,
      "reviewCount": 203,
      "rating": 4.5,
      "descriptionImages": ["/images/sports/running_shoes_1_1.jpg"],
      "content": "<p>쿠션감이 뛰어난 경량 러닝화.</p>",
      "stock": 27
    },
    {
      "id": 64,
      "name": "스마트 줄넘기",
      "company": "FitSync",
      "category": "SPORTS_LEISURE",
      "price": 29000,
      "thumbnailUrl": "/images/sports/jumprope_1.jpg",
      "isSoldOut": false,
      "isNew": false,
      "reviewCount": 74,
      "rating": 4.3,
      "descriptionImages": ["/images/sports/jumprope_1_1.jpg"],
      "content": "<p>운동량을 기록해주는 스마트 줄넘기.</p>",
      "stock": 55
    },
    {
      "id": 65,
      "name": "프로 트레이닝 장갑",
      "company": "GripMax",
      "category": "SPORTS_LEISURE",
      "price": 22000,
      "thumbnailUrl": "/images/sports/gloves_1.jpg",
      "isSoldOut": false,
      "isNew": false,
      "reviewCount": 61,
      "rating": 4.4,
      "descriptionImages": ["/images/sports/gloves_1_1.jpg"],
      "content": "<p>손바닥 보호와 그립감을 강화한 장갑.</p>",
      "stock": 73
    },
    {
      "id": 66,
      "name": "폼롤러 마사지",
      "company": "RelaxPro",
      "category": "SPORTS_LEISURE",
      "price": 27000,
      "thumbnailUrl": "/images/sports/foamroller_1.jpg",
      "isSoldOut": false,
      "isNew": false,
      "reviewCount": 119,
      "rating": 4.6,
      "descriptionImages": ["/images/sports/foamroller_1_1.jpg"],
      "content": "<p>근육 회복을 돕는 마사지 폼롤러.</p>",
      "stock": 39
    },
    {
      "id": 67,
      "name": "스포츠 스마트워치",
      "company": "MoveTech",
      "category": "SPORTS_LEISURE",
      "price": 159000,
      "thumbnailUrl": "/images/sports/watch_1.jpg",
      "isSoldOut": false,
      "isNew": true,
      "reviewCount": 312,
      "rating": 4.8,
      "descriptionImages": ["/images/sports/watch_1_1.jpg"],
      "content": "<p>운동 기록과 심박수를 실시간으로 측정.</p>",
      "stock": 21
    },
    {
      "id": 68,
      "name": "접이식 캠핑 체어",
      "company": "OutdoorLife",
      "category": "SPORTS_LEISURE",
      "price": 49000,
      "thumbnailUrl": "/images/sports/camping_chair_1.jpg",
      "isSoldOut": false,
      "isNew": false,
      "reviewCount": 97,
      "rating": 4.5,
      "descriptionImages": ["/images/sports/camping_chair_1_1.jpg"],
      "content": "<p>휴대성이 뛰어난 접이식 체어.</p>",
      "stock": 33
    },
    {
      "id": 69,
      "name": "등산용 백팩 30L",
      "company": "MountainGo",
      "category": "SPORTS_LEISURE",
      "price": 89000,
      "thumbnailUrl": "/images/sports/backpack_1.jpg",
      "isSoldOut": false,
      "isNew": false,
      "reviewCount": 145,
      "rating": 4.6,
      "descriptionImages": ["/images/sports/backpack_1_1.jpg"],
      "content": "<p>장시간 착용에도 편안한 등산 가방.</p>",
      "stock": 26
    },
    {
      "id": 70,
      "name": "스포츠 물병 스테인리스",
      "company": "HydroFit",
      "category": "SPORTS_LEISURE",
      "price": 18000,
      "thumbnailUrl": "/images/sports/bottle_1.jpg",
      "isSoldOut": false,
      "isNew": false,
      "reviewCount": 84,
      "rating": 4.2,
      "descriptionImages": ["/images/sports/bottle_1_1.jpg"],
      "content": "<p>보온·보냉 기능이 뛰어난 물병.</p>",
      "stock": 91
    },

    {
      "id": 71,
      "name": "다용도 수납 박스",
      "company": "EveryBox",
      "category": "OTHER",
      "price": 25000,
      "thumbnailUrl": "/images/other/storage_1.jpg",
      "isSoldOut": false,
      "isNew": false,
      "reviewCount": 66,
      "rating": 4.3,
      "descriptionImages": ["/images/other/storage_1_1.jpg"],
      "content": "<p>집안 정리를 위한 다용도 박스.</p>",
      "stock": 58
    },
    {
      "id": 72,
      "name": "차량용 방향제",
      "company": "FreshDrive",
      "category": "OTHER",
      "price": 15000,
      "thumbnailUrl": "/images/other/car_freshener_1.jpg",
      "isSoldOut": false,
      "isNew": true,
      "reviewCount": 42,
      "rating": 4.1,
      "descriptionImages": ["/images/other/car_freshener_1_1.jpg"],
      "content": "<p>은은한 향의 차량용 방향제.</p>",
      "stock": 120
    },
    {
      "id": 73,
      "name": "멀티 충전 케이블",
      "company": "LinkAll",
      "category": "OTHER",
      "price": 19000,
      "thumbnailUrl": "/images/other/cable_1.jpg",
      "isSoldOut": false,
      "isNew": false,
      "reviewCount": 201,
      "rating": 4.5,
      "descriptionImages": ["/images/other/cable_1_1.jpg"],
      "content": "<p>여러 기기를 동시에 충전 가능.</p>",
      "stock": 77
    },
    {
      "id": 74,
      "name": "탁상용 스탠드",
      "company": "BrightDesk",
      "category": "OTHER",
      "price": 34000,
      "thumbnailUrl": "/images/other/desk_lamp_1.jpg",
      "isSoldOut": false,
      "isNew": false,
      "reviewCount": 98,
      "rating": 4.4,
      "descriptionImages": ["/images/other/desk_lamp_1_1.jpg"],
      "content": "<p>눈부심을 줄인 LED 스탠드.</p>",
      "stock": 44
    },
    {
      "id": 75,
      "name": "노트북 파우치",
      "company": "SoftCase",
      "category": "OTHER",
      "price": 28000,
      "thumbnailUrl": "/images/other/laptop_pouch_1.jpg",
      "isSoldOut": false,
      "isNew": false,
      "reviewCount": 133,
      "rating": 4.6,
      "descriptionImages": ["/images/other/laptop_pouch_1_1.jpg"],
      "content": "<p>충격 흡수 소재로 제작된 파우치.</p>",
      "stock": 61
    },
    {
      "id": 76,
      "name": "휴대용 선풍기",
      "company": "CoolMate",
      "category": "OTHER",
      "price": 17000,
      "thumbnailUrl": "/images/other/fan_1.jpg",
      "isSoldOut": false,
      "isNew": true,
      "reviewCount": 189,
      "rating": 4.5,
      "descriptionImages": ["/images/other/fan_1_1.jpg"],
      "content": "<p>여름철 필수 휴대용 선풍기.</p>",
      "stock": 85
    },
    {
      "id": 77,
      "name": "다이어리 세트",
      "company": "PlanIt",
      "category": "OTHER",
      "price": 21000,
      "thumbnailUrl": "/images/other/diary_1.jpg",
      "isSoldOut": false,
      "isNew": false,
      "reviewCount": 54,
      "rating": 4.2,
      "descriptionImages": ["/images/other/diary_1_1.jpg"],
      "content": "<p>일정 관리에 최적화된 다이어리.</p>",
      "stock": 46
    },
    {
      "id": 78,
      "name": "스마트폰 거치대",
      "company": "HoldUp",
      "category": "OTHER",
      "price": 13000,
      "thumbnailUrl": "/images/other/phone_holder_1.jpg",
      "isSoldOut": false,
      "isNew": false,
      "reviewCount": 167,
      "rating": 4.4,
      "descriptionImages": ["/images/other/phone_holder_1_1.jpg"],
      "content": "<p>각도 조절이 자유로운 거치대.</p>",
      "stock": 99
    },
    {
      "id": 79,
      "name": "미니 공기청정기",
      "company": "PureAir",
      "category": "OTHER",
      "price": 59000,
      "thumbnailUrl": "/images/other/air_purifier_1.jpg",
      "isSoldOut": false,
      "isNew": true,
      "reviewCount": 121,
      "rating": 4.6,
      "descriptionImages": ["/images/other/air_purifier_1_1.jpg"],
      "content": "<p>책상 위에 두기 좋은 공기청정기.</p>",
      "stock": 24
    },
    {
      "id": 80,
      "name": "USB 허브 6포트",
      "company": "Connectix",
      "category": "OTHER",
      "price": 32000,
      "thumbnailUrl": "/images/other/usb_hub_1.jpg",
      "isSoldOut": false,
      "isNew": false,
      "reviewCount": 211,
      "rating": 4.7,
      "descriptionImages": ["/images/other/usb_hub_1_1.jpg"],
      "content": "<p>확장성이 뛰어난 USB 허브.</p>",
      "stock": 52
    }
  ]
}
